 	{ "type" : "FeatureCollection",
		"features" : [
		 		{ "type" : "Feature",
				"geometry" : {
					"type" : "Point",
					"coordinates" : [7.57066,44.89458]},
			"properties" : { "ANNO":"2010","ID_SEZIONE":"3828","ISTAT_COMUNE_SEZ":"1065","COMUNE_SEZ":"CASTAGNOLE PIEMONTE","PROVINCIA":"TO","ID_CENTRALE":"345","NOME_CENTRALE":"CASTAGNOLE PIEMONTE","ISTAT_COMUNE_CENTR":"1065","COMUNE_CENTR":"CASTAGNOLE PIEMONTE","PROVINCIA_CENTR":"TO","INDIRIZZO_CENTRALE":"STRADA DEL FALETTO","LATITUDINE_SEZIONE":"44.89458","LONGITUDINE_SEZIONE":"7.57066","POS_X_SEZIONE":"387139.89357","POS_Y_SEZIONE":"4972233.73110","LATITUDINE_CENTRALE":"44.90138","LONGITUDINE_CENTRALE":"7.56065","POS_X_CENTRALE":"386362.69539","POS_Y_CENTRALE":"4973002.17462","TIPO_ADSL":"ADSL_M","DESCRIZIONE_TIPO_ADSL":"ADSL Mini","DISTANZA_CALCOLATA":"1092.95","CLASSE_DISTANZA":"900-1299","POTENZA_SEGNALE":"0.64","POPOLAZIONE_SEZIONE": "32"}
			},
		 		{ "type" : "Feature",
				"geometry" : {
					"type" : "Point",
					"coordinates" : [7.54687,44.89873]},
			"properties" : { "ANNO":"2010","ID_SEZIONE":"5971","ISTAT_COMUNE_SEZ":"1065","COMUNE_SEZ":"CASTAGNOLE PIEMONTE","PROVINCIA":"TO","ID_CENTRALE":"345","NOME_CENTRALE":"CASTAGNOLE PIEMONTE","ISTAT_COMUNE_CENTR":"1065","COMUNE_CENTR":"CASTAGNOLE PIEMONTE","PROVINCIA_CENTR":"TO","INDIRIZZO_CENTRALE":"STRADA DEL FALETTO","LATITUDINE_SEZIONE":"44.89873","LONGITUDINE_SEZIONE":"7.54687","POS_X_SEZIONE":"385269.35686","POS_Y_SEZIONE":"4972727.23715","LATITUDINE_CENTRALE":"44.90138","LONGITUDINE_CENTRALE":"7.56065","POS_X_CENTRALE":"386362.69539","POS_Y_CENTRALE":"4973002.17462","TIPO_ADSL":"ADSL_M","DESCRIZIONE_TIPO_ADSL":"ADSL Mini","DISTANZA_CALCOLATA":"1127.38","CLASSE_DISTANZA":"900-1299","POTENZA_SEGNALE":"0.64","POPOLAZIONE_SEZIONE": "34"}
			},
		 		{ "type" : "Feature",
				"geometry" : {
					"type" : "Point",
					"coordinates" : [7.56135,44.88309]},
			"properties" : { "ANNO":"2010","ID_SEZIONE":"6883","ISTAT_COMUNE_SEZ":"1065","COMUNE_SEZ":"CASTAGNOLE PIEMONTE","PROVINCIA":"TO","ID_CENTRALE":"345","NOME_CENTRALE":"CASTAGNOLE PIEMONTE","ISTAT_COMUNE_CENTR":"1065","COMUNE_CENTR":"CASTAGNOLE PIEMONTE","PROVINCIA_CENTR":"TO","INDIRIZZO_CENTRALE":"STRADA DEL FALETTO","LATITUDINE_SEZIONE":"44.88309","LONGITUDINE_SEZIONE":"7.56135","POS_X_SEZIONE":"386381.60262","POS_Y_SEZIONE":"4970969.70191","LATITUDINE_CENTRALE":"44.90138","LONGITUDINE_CENTRALE":"7.56065","POS_X_CENTRALE":"386362.69539","POS_Y_CENTRALE":"4973002.17462","TIPO_ADSL":"ADSL_M","DESCRIZIONE_TIPO_ADSL":"ADSL Mini","DISTANZA_CALCOLATA":"2032.56","CLASSE_DISTANZA":"1700-2099","POTENZA_SEGNALE":"0.64","POPOLAZIONE_SEZIONE": "13"}
			},
		 		{ "type" : "Feature",
				"geometry" : {
					"type" : "Point",
					"coordinates" : [7.56547,44.91052]},
			"properties" : { "ANNO":"2010","ID_SEZIONE":"8060","ISTAT_COMUNE_SEZ":"1065","COMUNE_SEZ":"CASTAGNOLE PIEMONTE","PROVINCIA":"TO","ID_CENTRALE":"345","NOME_CENTRALE":"CASTAGNOLE PIEMONTE","ISTAT_COMUNE_CENTR":"1065","COMUNE_CENTR":"CASTAGNOLE PIEMONTE","PROVINCIA_CENTR":"TO","INDIRIZZO_CENTRALE":"STRADA DEL FALETTO","LATITUDINE_SEZIONE":"44.91052","LONGITUDINE_SEZIONE":"7.56547","POS_X_SEZIONE":"386761.15129","POS_Y_SEZIONE":"4974011.26915","LATITUDINE_CENTRALE":"44.90138","LONGITUDINE_CENTRALE":"7.56065","POS_X_CENTRALE":"386362.69539","POS_Y_CENTRALE":"4973002.17462","TIPO_ADSL":"ADSL_M","DESCRIZIONE_TIPO_ADSL":"ADSL Mini","DISTANZA_CALCOLATA":"1084.91","CLASSE_DISTANZA":"900-1299","POTENZA_SEGNALE":"0.64","POPOLAZIONE_SEZIONE": "42"}
			},
		 		{ "type" : "Feature",
				"geometry" : {
					"type" : "Point",
					"coordinates" : [7.57684,44.89246]},
			"properties" : { "ANNO":"2010","ID_SEZIONE":"11841","ISTAT_COMUNE_SEZ":"1065","COMUNE_SEZ":"CASTAGNOLE PIEMONTE","PROVINCIA":"TO","ID_CENTRALE":"345","NOME_CENTRALE":"CASTAGNOLE PIEMONTE","ISTAT_COMUNE_CENTR":"1065","COMUNE_CENTR":"CASTAGNOLE PIEMONTE","PROVINCIA_CENTR":"TO","INDIRIZZO_CENTRALE":"STRADA DEL FALETTO","LATITUDINE_SEZIONE":"44.89246","LONGITUDINE_SEZIONE":"7.57684","POS_X_SEZIONE":"387623.20774","POS_Y_SEZIONE":"4971989.72675","LATITUDINE_CENTRALE":"44.90138","LONGITUDINE_CENTRALE":"7.56065","POS_X_CENTRALE":"386362.69539","POS_Y_CENTRALE":"4973002.17462","TIPO_ADSL":"ADSL_M","DESCRIZIONE_TIPO_ADSL":"ADSL Mini","DISTANZA_CALCOLATA":"1616.77","CLASSE_DISTANZA":"1300-1699","POTENZA_SEGNALE":"0.64","POPOLAZIONE_SEZIONE": "13"}
			},
		 		{ "type" : "Feature",
				"geometry" : {
					"type" : "Point",
					"coordinates" : [7.57582,44.88202]},
			"properties" : { "ANNO":"2010","ID_SEZIONE":"13161","ISTAT_COMUNE_SEZ":"1065","COMUNE_SEZ":"CASTAGNOLE PIEMONTE","PROVINCIA":"TO","ID_CENTRALE":"345","NOME_CENTRALE":"CASTAGNOLE PIEMONTE","ISTAT_COMUNE_CENTR":"1065","COMUNE_CENTR":"CASTAGNOLE PIEMONTE","PROVINCIA_CENTR":"TO","INDIRIZZO_CENTRALE":"STRADA DEL FALETTO","LATITUDINE_SEZIONE":"44.88202","LONGITUDINE_SEZIONE":"7.57582","POS_X_SEZIONE":"387522.60742","POS_Y_SEZIONE":"4970830.70108","LATITUDINE_CENTRALE":"44.90138","LONGITUDINE_CENTRALE":"7.56065","POS_X_CENTRALE":"386362.69539","POS_Y_CENTRALE":"4973002.17462","TIPO_ADSL":"ADSL_M","DESCRIZIONE_TIPO_ADSL":"ADSL Mini","DISTANZA_CALCOLATA":"2461.85","CLASSE_DISTANZA":"2100-2499","POTENZA_SEGNALE":"0.64","POPOLAZIONE_SEZIONE": "10"}
			},
		 		{ "type" : "Feature",
				"geometry" : {
					"type" : "Point",
					"coordinates" : [7.59095,44.88520]},
			"properties" : { "ANNO":"2010","ID_SEZIONE":"15245","ISTAT_COMUNE_SEZ":"1065","COMUNE_SEZ":"CASTAGNOLE PIEMONTE","PROVINCIA":"TO","ID_CENTRALE":"345","NOME_CENTRALE":"CASTAGNOLE PIEMONTE","ISTAT_COMUNE_CENTR":"1065","COMUNE_CENTR":"CASTAGNOLE PIEMONTE","PROVINCIA_CENTR":"TO","INDIRIZZO_CENTRALE":"STRADA DEL FALETTO","LATITUDINE_SEZIONE":"44.88520","LONGITUDINE_SEZIONE":"7.59095","POS_X_SEZIONE":"388723.57664","POS_Y_SEZIONE":"4971163.71254","LATITUDINE_CENTRALE":"44.90138","LONGITUDINE_CENTRALE":"7.56065","POS_X_CENTRALE":"386362.69539","POS_Y_CENTRALE":"4973002.17462","TIPO_ADSL":"ADSL_M","DESCRIZIONE_TIPO_ADSL":"ADSL Mini","DISTANZA_CALCOLATA":"2992.27","CLASSE_DISTANZA":"2900-3299","POTENZA_SEGNALE":"0.64","POPOLAZIONE_SEZIONE": "77"}
			},
		 		{ "type" : "Feature",
				"geometry" : {
					"type" : "Point",
					"coordinates" : [7.57032,44.90020]},
			"properties" : { "ANNO":"2010","ID_SEZIONE":"18062","ISTAT_COMUNE_SEZ":"1065","COMUNE_SEZ":"CASTAGNOLE PIEMONTE","PROVINCIA":"TO","ID_CENTRALE":"345","NOME_CENTRALE":"CASTAGNOLE PIEMONTE","ISTAT_COMUNE_CENTR":"1065","COMUNE_CENTR":"CASTAGNOLE PIEMONTE","PROVINCIA_CENTR":"TO","INDIRIZZO_CENTRALE":"STRADA DEL FALETTO","LATITUDINE_SEZIONE":"44.90020","LONGITUDINE_SEZIONE":"7.57032","POS_X_SEZIONE":"387123.77171","POS_Y_SEZIONE":"4972857.74492","LATITUDINE_CENTRALE":"44.90138","LONGITUDINE_CENTRALE":"7.56065","POS_X_CENTRALE":"386362.69539","POS_Y_CENTRALE":"4973002.17462","TIPO_ADSL":"ADSL_M","DESCRIZIONE_TIPO_ADSL":"ADSL Mini","DISTANZA_CALCOLATA":"774.66","CLASSE_DISTANZA":"500-899","POTENZA_SEGNALE":"0.64","POPOLAZIONE_SEZIONE": "672"}
			},
		 		{ "type" : "Feature",
				"geometry" : {
					"type" : "Point",
					"coordinates" : [7.56322,44.89908]},
			"properties" : { "ANNO":"2010","ID_SEZIONE":"18063","ISTAT_COMUNE_SEZ":"1065","COMUNE_SEZ":"CASTAGNOLE PIEMONTE","PROVINCIA":"TO","ID_CENTRALE":"345","NOME_CENTRALE":"CASTAGNOLE PIEMONTE","ISTAT_COMUNE_CENTR":"1065","COMUNE_CENTR":"CASTAGNOLE PIEMONTE","PROVINCIA_CENTR":"TO","INDIRIZZO_CENTRALE":"STRADA DEL FALETTO","LATITUDINE_SEZIONE":"44.89908","LONGITUDINE_SEZIONE":"7.56322","POS_X_SEZIONE":"386561.42470","POS_Y_SEZIONE":"4972743.24073","LATITUDINE_CENTRALE":"44.90138","LONGITUDINE_CENTRALE":"7.56065","POS_X_CENTRALE":"386362.69539","POS_Y_CENTRALE":"4973002.17462","TIPO_ADSL":"ADSL_M","DESCRIZIONE_TIPO_ADSL":"ADSL Mini","DISTANZA_CALCOLATA":"326.40","CLASSE_DISTANZA":"100-499","POTENZA_SEGNALE":"0.64","POPOLAZIONE_SEZIONE": "396"}
			},
		 		{ "type" : "Feature",
				"geometry" : {
					"type" : "Point",
					"coordinates" : [7.56625,44.88891]},
			"properties" : { "ANNO":"2010","ID_SEZIONE":"19486","ISTAT_COMUNE_SEZ":"1065","COMUNE_SEZ":"CASTAGNOLE PIEMONTE","PROVINCIA":"TO","ID_CENTRALE":"345","NOME_CENTRALE":"CASTAGNOLE PIEMONTE","ISTAT_COMUNE_CENTR":"1065","COMUNE_CENTR":"CASTAGNOLE PIEMONTE","PROVINCIA_CENTR":"TO","INDIRIZZO_CENTRALE":"STRADA DEL FALETTO","LATITUDINE_SEZIONE":"44.88891","LONGITUDINE_SEZIONE":"7.56625","POS_X_SEZIONE":"386779.98317","POS_Y_SEZIONE":"4971609.71676","LATITUDINE_CENTRALE":"44.90138","LONGITUDINE_CENTRALE":"7.56065","POS_X_CENTRALE":"386362.69539","POS_Y_CENTRALE":"4973002.17462","TIPO_ADSL":"ADSL_M","DESCRIZIONE_TIPO_ADSL":"ADSL Mini","DISTANZA_CALCOLATA":"1453.64","CLASSE_DISTANZA":"1300-1699","POTENZA_SEGNALE":"0.64","POPOLAZIONE_SEZIONE": "20"}
			},
		 		{ "type" : "Feature",
				"geometry" : {
					"type" : "Point",
					"coordinates" : [7.56791,44.89765]},
			"properties" : { "ANNO":"2010","ID_SEZIONE":"21687","ISTAT_COMUNE_SEZ":"1065","COMUNE_SEZ":"CASTAGNOLE PIEMONTE","PROVINCIA":"TO","ID_CENTRALE":"345","NOME_CENTRALE":"CASTAGNOLE PIEMONTE","ISTAT_COMUNE_CENTR":"1065","COMUNE_CENTR":"CASTAGNOLE PIEMONTE","PROVINCIA_CENTR":"TO","INDIRIZZO_CENTRALE":"STRADA DEL FALETTO","LATITUDINE_SEZIONE":"44.89765","LONGITUDINE_SEZIONE":"7.56791","POS_X_SEZIONE":"386928.39456","POS_Y_SEZIONE":"4972577.73827","LATITUDINE_CENTRALE":"44.90138","LONGITUDINE_CENTRALE":"7.56065","POS_X_CENTRALE":"386362.69539","POS_Y_CENTRALE":"4973002.17462","TIPO_ADSL":"ADSL_M","DESCRIZIONE_TIPO_ADSL":"ADSL Mini","DISTANZA_CALCOLATA":"707.22","CLASSE_DISTANZA":"500-899","POTENZA_SEGNALE":"0.64","POPOLAZIONE_SEZIONE": "478"}
			},
		 		{ "type" : "Feature",
				"geometry" : {
					"type" : "Point",
					"coordinates" : [7.59453,44.89357]},
			"properties" : { "ANNO":"2010","ID_SEZIONE":"21688","ISTAT_COMUNE_SEZ":"1065","COMUNE_SEZ":"CASTAGNOLE PIEMONTE","PROVINCIA":"TO","ID_CENTRALE":"345","NOME_CENTRALE":"CASTAGNOLE PIEMONTE","ISTAT_COMUNE_CENTR":"1065","COMUNE_CENTR":"CASTAGNOLE PIEMONTE","PROVINCIA_CENTR":"TO","INDIRIZZO_CENTRALE":"STRADA DEL FALETTO","LATITUDINE_SEZIONE":"44.89357","LONGITUDINE_SEZIONE":"7.59453","POS_X_SEZIONE":"389022.32966","POS_Y_SEZIONE":"4972087.73379","LATITUDINE_CENTRALE":"44.90138","LONGITUDINE_CENTRALE":"7.56065","POS_X_CENTRALE":"386362.69539","POS_Y_CENTRALE":"4973002.17462","TIPO_ADSL":"ADSL_M","DESCRIZIONE_TIPO_ADSL":"ADSL Mini","DISTANZA_CALCOLATA":"2812.45","CLASSE_DISTANZA":"2500-2899","POTENZA_SEGNALE":"0.64","POPOLAZIONE_SEZIONE": "11"}
			},
		 		{ "type" : "Feature",
				"geometry" : {
					"type" : "Point",
					"coordinates" : [7.54822,44.88494]},
			"properties" : { "ANNO":"2010","ID_SEZIONE":"26659","ISTAT_COMUNE_SEZ":"1065","COMUNE_SEZ":"CASTAGNOLE PIEMONTE","PROVINCIA":"TO","ID_CENTRALE":"345","NOME_CENTRALE":"CASTAGNOLE PIEMONTE","ISTAT_COMUNE_CENTR":"1065","COMUNE_CENTR":"CASTAGNOLE PIEMONTE","PROVINCIA_CENTR":"TO","INDIRIZZO_CENTRALE":"STRADA DEL FALETTO","LATITUDINE_SEZIONE":"44.88494","LONGITUDINE_SEZIONE":"7.54822","POS_X_SEZIONE":"385348.38048","POS_Y_SEZIONE":"4971193.70447","LATITUDINE_CENTRALE":"44.90138","LONGITUDINE_CENTRALE":"7.56065","POS_X_CENTRALE":"386362.69539","POS_Y_CENTRALE":"4973002.17462","TIPO_ADSL":"ADSL_M","DESCRIZIONE_TIPO_ADSL":"ADSL Mini","DISTANZA_CALCOLATA":"2073.5","CLASSE_DISTANZA":"1700-2099","POTENZA_SEGNALE":"0.64","POPOLAZIONE_SEZIONE": "19"}
			},
		 		{ "type" : "Feature",
				"geometry" : {
					"type" : "Point",
					"coordinates" : [7.54644,44.90656]},
			"properties" : { "ANNO":"2010","ID_SEZIONE":"26914","ISTAT_COMUNE_SEZ":"1065","COMUNE_SEZ":"CASTAGNOLE PIEMONTE","PROVINCIA":"TO","ID_CENTRALE":"345","NOME_CENTRALE":"CASTAGNOLE PIEMONTE","ISTAT_COMUNE_CENTR":"1065","COMUNE_CENTR":"CASTAGNOLE PIEMONTE","PROVINCIA_CENTR":"TO","INDIRIZZO_CENTRALE":"STRADA DEL FALETTO","LATITUDINE_SEZIONE":"44.90656","LONGITUDINE_SEZIONE":"7.54644","POS_X_SEZIONE":"385251.01753","POS_Y_SEZIONE":"4973598.25616","LATITUDINE_CENTRALE":"44.90138","LONGITUDINE_CENTRALE":"7.56065","POS_X_CENTRALE":"386362.69539","POS_Y_CENTRALE":"4973002.17462","TIPO_ADSL":"ADSL_M","DESCRIZIONE_TIPO_ADSL":"ADSL Mini","DISTANZA_CALCOLATA":"1261.4","CLASSE_DISTANZA":"900-1299","POTENZA_SEGNALE":"0.64","POPOLAZIONE_SEZIONE": "33"}
			},
		 		{ "type" : "Feature",
				"geometry" : {
					"type" : "Point",
					"coordinates" : [7.54761,44.88942]},
			"properties" : { "ANNO":"2010","ID_SEZIONE":"28387","ISTAT_COMUNE_SEZ":"1065","COMUNE_SEZ":"CASTAGNOLE PIEMONTE","PROVINCIA":"TO","ID_CENTRALE":"345","NOME_CENTRALE":"CASTAGNOLE PIEMONTE","ISTAT_COMUNE_CENTR":"1065","COMUNE_CENTR":"CASTAGNOLE PIEMONTE","PROVINCIA_CENTR":"TO","INDIRIZZO_CENTRALE":"STRADA DEL FALETTO","LATITUDINE_SEZIONE":"44.88942","LONGITUDINE_SEZIONE":"7.54761","POS_X_SEZIONE":"385309.07065","POS_Y_SEZIONE":"4971692.71503","LATITUDINE_CENTRALE":"44.90138","LONGITUDINE_CENTRALE":"7.56065","POS_X_CENTRALE":"386362.69539","POS_Y_CENTRALE":"4973002.17462","TIPO_ADSL":"ADSL_M","DESCRIZIONE_TIPO_ADSL":"ADSL Mini","DISTANZA_CALCOLATA":"1680.72","CLASSE_DISTANZA":"1300-1699","POTENZA_SEGNALE":"0.64","POPOLAZIONE_SEZIONE": "24"}
			},
		 		{ "type" : "Feature",
				"geometry" : {
					"type" : "Point",
					"coordinates" : [7.58781,44.88286]},
			"properties" : { "ANNO":"2010","ID_SEZIONE":"31929","ISTAT_COMUNE_SEZ":"1065","COMUNE_SEZ":"CASTAGNOLE PIEMONTE","PROVINCIA":"TO","ID_CENTRALE":"345","NOME_CENTRALE":"CASTAGNOLE PIEMONTE","ISTAT_COMUNE_CENTR":"1065","COMUNE_CENTR":"CASTAGNOLE PIEMONTE","PROVINCIA_CENTR":"TO","INDIRIZZO_CENTRALE":"STRADA DEL FALETTO","LATITUDINE_SEZIONE":"44.88286","LONGITUDINE_SEZIONE":"7.58781","POS_X_SEZIONE":"388471.16883","POS_Y_SEZIONE":"4970907.20617","LATITUDINE_CENTRALE":"44.90138","LONGITUDINE_CENTRALE":"7.56065","POS_X_CENTRALE":"386362.69539","POS_Y_CENTRALE":"4973002.17462","TIPO_ADSL":"ADSL_M","DESCRIZIONE_TIPO_ADSL":"ADSL Mini","DISTANZA_CALCOLATA":"2972.3","CLASSE_DISTANZA":"2900-3299","POTENZA_SEGNALE":"0.64","POPOLAZIONE_SEZIONE": "1"}
			}
		 		]
	}
		