 	{ "type" : "FeatureCollection",
		"features" : [
		 		{ "type" : "Feature",
				"geometry" : {
					"type" : "Point",
					"coordinates" : [7.60650,44.37563]},
			"properties" : { "ANNO":"2010","ID_SEZIONE":"445","ISTAT_COMUNE_SEZ":"4163","COMUNE_SEZ":"PEVERAGNO","PROVINCIA":"CN","ID_CENTRALE":"135","NOME_CENTRALE":"BEINETTE","ISTAT_COMUNE_CENTR":"4016","COMUNE_CENTR":"BEINETTE","PROVINCIA_CENTR":"CN","INDIRIZZO_CENTRALE":"PIAZZA DIVISIONE CUNEENSE","LATITUDINE_SEZIONE":"44.37563","LONGITUDINE_SEZIONE":"7.60650","POS_X_SEZIONE":"388984.59219","POS_Y_SEZIONE":"4914539.13700","LATITUDINE_CENTRALE":"44.36157","LONGITUDINE_CENTRALE":"7.64699","POS_X_CENTRALE":"392184.00000","POS_Y_CENTRALE":"4912923.00000","TIPO_ADSL":"ADSL_1","DESCRIZIONE_TIPO_ADSL":"ADSL (8 mega)","DISTANZA_CALCOLATA":"3584.43","CLASSE_DISTANZA":"3300-3699","POTENZA_SEGNALE":"3999.63","POPOLAZIONE_SEZIONE": "116"}
			},
		 		{ "type" : "Feature",
				"geometry" : {
					"type" : "Point",
					"coordinates" : [7.62690,44.37512]},
			"properties" : { "ANNO":"2010","ID_SEZIONE":"447","ISTAT_COMUNE_SEZ":"4016","COMUNE_SEZ":"BEINETTE","PROVINCIA":"CN","ID_CENTRALE":"135","NOME_CENTRALE":"BEINETTE","ISTAT_COMUNE_CENTR":"4016","COMUNE_CENTR":"BEINETTE","PROVINCIA_CENTR":"CN","INDIRIZZO_CENTRALE":"PIAZZA DIVISIONE CUNEENSE","LATITUDINE_SEZIONE":"44.37512","LONGITUDINE_SEZIONE":"7.62690","POS_X_SEZIONE":"390608.77498","POS_Y_SEZIONE":"4914454.64061","LATITUDINE_CENTRALE":"44.36157","LONGITUDINE_CENTRALE":"7.64699","POS_X_CENTRALE":"392184.00000","POS_Y_CENTRALE":"4912923.00000","TIPO_ADSL":"ADSL_1","DESCRIZIONE_TIPO_ADSL":"ADSL (8 mega)","DISTANZA_CALCOLATA":"2197.1","CLASSE_DISTANZA":"2100-2499","POTENZA_SEGNALE":"6500.38","POPOLAZIONE_SEZIONE": "20"}
			},
		 		{ "type" : "Feature",
				"geometry" : {
					"type" : "Point",
					"coordinates" : [7.66890,44.37077]},
			"properties" : { "ANNO":"2010","ID_SEZIONE":"3928","ISTAT_COMUNE_SEZ":"4016","COMUNE_SEZ":"BEINETTE","PROVINCIA":"CN","ID_CENTRALE":"135","NOME_CENTRALE":"BEINETTE","ISTAT_COMUNE_CENTR":"4016","COMUNE_CENTR":"BEINETTE","PROVINCIA_CENTR":"CN","INDIRIZZO_CENTRALE":"PIAZZA DIVISIONE CUNEENSE","LATITUDINE_SEZIONE":"44.37077","LONGITUDINE_SEZIONE":"7.66890","POS_X_SEZIONE":"393946.49018","POS_Y_SEZIONE":"4913916.64842","LATITUDINE_CENTRALE":"44.36157","LONGITUDINE_CENTRALE":"7.64699","POS_X_CENTRALE":"392184.00000","POS_Y_CENTRALE":"4912923.00000","TIPO_ADSL":"ADSL_1","DESCRIZIONE_TIPO_ADSL":"ADSL (8 mega)","DISTANZA_CALCOLATA":"2023.29","CLASSE_DISTANZA":"1700-2099","POTENZA_SEGNALE":"6874.88","POPOLAZIONE_SEZIONE": "10"}
			},
		 		{ "type" : "Feature",
				"geometry" : {
					"type" : "Point",
					"coordinates" : [7.68022,44.37740]},
			"properties" : { "ANNO":"2010","ID_SEZIONE":"6766","ISTAT_COMUNE_SEZ":"4016","COMUNE_SEZ":"BEINETTE","PROVINCIA":"CN","ID_CENTRALE":"135","NOME_CENTRALE":"BEINETTE","ISTAT_COMUNE_CENTR":"4016","COMUNE_CENTR":"BEINETTE","PROVINCIA_CENTR":"CN","INDIRIZZO_CENTRALE":"PIAZZA DIVISIONE CUNEENSE","LATITUDINE_SEZIONE":"44.37740","LONGITUDINE_SEZIONE":"7.68022","POS_X_SEZIONE":"394860.21869","POS_Y_SEZIONE":"4914638.15012","LATITUDINE_CENTRALE":"44.36157","LONGITUDINE_CENTRALE":"7.64699","POS_X_CENTRALE":"392184.00000","POS_Y_CENTRALE":"4912923.00000","TIPO_ADSL":"ADSL_1","DESCRIZIONE_TIPO_ADSL":"ADSL (8 mega)","DISTANZA_CALCOLATA":"3178.66","CLASSE_DISTANZA":"2900-3299","POTENZA_SEGNALE":"4999.75","POPOLAZIONE_SEZIONE": "8"}
			},
		 		{ "type" : "Feature",
				"geometry" : {
					"type" : "Point",
					"coordinates" : [7.64033,44.36127]},
			"properties" : { "ANNO":"2010","ID_SEZIONE":"9063","ISTAT_COMUNE_SEZ":"4016","COMUNE_SEZ":"BEINETTE","PROVINCIA":"CN","ID_CENTRALE":"135","NOME_CENTRALE":"BEINETTE","ISTAT_COMUNE_CENTR":"4016","COMUNE_CENTR":"BEINETTE","PROVINCIA_CENTR":"CN","INDIRIZZO_CENTRALE":"PIAZZA DIVISIONE CUNEENSE","LATITUDINE_SEZIONE":"44.36127","LONGITUDINE_SEZIONE":"7.64033","POS_X_SEZIONE":"391652.68461","POS_Y_SEZIONE":"4912898.14218","LATITUDINE_CENTRALE":"44.36157","LONGITUDINE_CENTRALE":"7.64699","POS_X_CENTRALE":"392184.00000","POS_Y_CENTRALE":"4912923.00000","TIPO_ADSL":"ADSL_1","DESCRIZIONE_TIPO_ADSL":"ADSL (8 mega)","DISTANZA_CALCOLATA":"531.90","CLASSE_DISTANZA":"500-899","POTENZA_SEGNALE":"7000","POPOLAZIONE_SEZIONE": "187"}
			},
		 		{ "type" : "Feature",
				"geometry" : {
					"type" : "Point",
					"coordinates" : [7.62170,44.37277]},
			"properties" : { "ANNO":"2010","ID_SEZIONE":"9903","ISTAT_COMUNE_SEZ":"4016","COMUNE_SEZ":"BEINETTE","PROVINCIA":"CN","ID_CENTRALE":"135","NOME_CENTRALE":"BEINETTE","ISTAT_COMUNE_CENTR":"4016","COMUNE_CENTR":"BEINETTE","PROVINCIA_CENTR":"CN","INDIRIZZO_CENTRALE":"PIAZZA DIVISIONE CUNEENSE","LATITUDINE_SEZIONE":"44.37277","LONGITUDINE_SEZIONE":"7.62170","POS_X_SEZIONE":"390190.18938","POS_Y_SEZIONE":"4914201.13968","LATITUDINE_CENTRALE":"44.36157","LONGITUDINE_CENTRALE":"7.64699","POS_X_CENTRALE":"392184.00000","POS_Y_CENTRALE":"4912923.00000","TIPO_ADSL":"ADSL_1","DESCRIZIONE_TIPO_ADSL":"ADSL (8 mega)","DISTANZA_CALCOLATA":"2368.32","CLASSE_DISTANZA":"2100-2499","POTENZA_SEGNALE":"6500.38","POPOLAZIONE_SEZIONE": "21"}
			},
		 		{ "type" : "Feature",
				"geometry" : {
					"type" : "Point",
					"coordinates" : [7.64783,44.36484]},
			"properties" : { "ANNO":"2010","ID_SEZIONE":"10202","ISTAT_COMUNE_SEZ":"4016","COMUNE_SEZ":"BEINETTE","PROVINCIA":"CN","ID_CENTRALE":"135","NOME_CENTRALE":"BEINETTE","ISTAT_COMUNE_CENTR":"4016","COMUNE_CENTR":"BEINETTE","PROVINCIA_CENTR":"CN","INDIRIZZO_CENTRALE":"PIAZZA DIVISIONE CUNEENSE","LATITUDINE_SEZIONE":"44.36484","LONGITUDINE_SEZIONE":"7.64783","POS_X_SEZIONE":"392256.88967","POS_Y_SEZIONE":"4913284.64381","LATITUDINE_CENTRALE":"44.36157","LONGITUDINE_CENTRALE":"7.64699","POS_X_CENTRALE":"392184.00000","POS_Y_CENTRALE":"4912923.00000","TIPO_ADSL":"ADSL_1","DESCRIZIONE_TIPO_ADSL":"ADSL (8 mega)","DISTANZA_CALCOLATA":"368.92","CLASSE_DISTANZA":"100-499","POTENZA_SEGNALE":"7000","POPOLAZIONE_SEZIONE": "571"}
			},
		 		{ "type" : "Feature",
				"geometry" : {
					"type" : "Point",
					"coordinates" : [7.66074,44.36872]},
			"properties" : { "ANNO":"2010","ID_SEZIONE":"10714","ISTAT_COMUNE_SEZ":"4016","COMUNE_SEZ":"BEINETTE","PROVINCIA":"CN","ID_CENTRALE":"135","NOME_CENTRALE":"BEINETTE","ISTAT_COMUNE_CENTR":"4016","COMUNE_CENTR":"BEINETTE","PROVINCIA_CENTR":"CN","INDIRIZZO_CENTRALE":"PIAZZA DIVISIONE CUNEENSE","LATITUDINE_SEZIONE":"44.36872","LONGITUDINE_SEZIONE":"7.66074","POS_X_SEZIONE":"393292.93652","POS_Y_SEZIONE":"4913699.64644","LATITUDINE_CENTRALE":"44.36157","LONGITUDINE_CENTRALE":"7.64699","POS_X_CENTRALE":"392184.00000","POS_Y_CENTRALE":"4912923.00000","TIPO_ADSL":"ADSL_1","DESCRIZIONE_TIPO_ADSL":"ADSL (8 mega)","DISTANZA_CALCOLATA":"1353.85","CLASSE_DISTANZA":"1300-1699","POTENZA_SEGNALE":"7000","POPOLAZIONE_SEZIONE": "77"}
			},
		 		{ "type" : "Feature",
				"geometry" : {
					"type" : "Point",
					"coordinates" : [7.67582,44.37781]},
			"properties" : { "ANNO":"2010","ID_SEZIONE":"11920","ISTAT_COMUNE_SEZ":"4016","COMUNE_SEZ":"BEINETTE","PROVINCIA":"CN","ID_CENTRALE":"135","NOME_CENTRALE":"BEINETTE","ISTAT_COMUNE_CENTR":"4016","COMUNE_CENTR":"BEINETTE","PROVINCIA_CENTR":"CN","INDIRIZZO_CENTRALE":"PIAZZA DIVISIONE CUNEENSE","LATITUDINE_SEZIONE":"44.37781","LONGITUDINE_SEZIONE":"7.67582","POS_X_SEZIONE":"394510.59386","POS_Y_SEZIONE":"4914689.64912","LATITUDINE_CENTRALE":"44.36157","LONGITUDINE_CENTRALE":"7.64699","POS_X_CENTRALE":"392184.00000","POS_Y_CENTRALE":"4912923.00000","TIPO_ADSL":"ADSL_1","DESCRIZIONE_TIPO_ADSL":"ADSL (8 mega)","DISTANZA_CALCOLATA":"2921.32","CLASSE_DISTANZA":"2900-3299","POTENZA_SEGNALE":"4999.75","POPOLAZIONE_SEZIONE": "10"}
			},
		 		{ "type" : "Feature",
				"geometry" : {
					"type" : "Point",
					"coordinates" : [7.66589,44.38248]},
			"properties" : { "ANNO":"2010","ID_SEZIONE":"17579","ISTAT_COMUNE_SEZ":"4016","COMUNE_SEZ":"BEINETTE","PROVINCIA":"CN","ID_CENTRALE":"135","NOME_CENTRALE":"BEINETTE","ISTAT_COMUNE_CENTR":"4016","COMUNE_CENTR":"BEINETTE","PROVINCIA_CENTR":"CN","INDIRIZZO_CENTRALE":"PIAZZA DIVISIONE CUNEENSE","LATITUDINE_SEZIONE":"44.38248","LONGITUDINE_SEZIONE":"7.66589","POS_X_SEZIONE":"393728.42836","POS_Y_SEZIONE":"4915221.14762","LATITUDINE_CENTRALE":"44.36157","LONGITUDINE_CENTRALE":"7.64699","POS_X_CENTRALE":"392184.00000","POS_Y_CENTRALE":"4912923.00000","TIPO_ADSL":"ADSL_1","DESCRIZIONE_TIPO_ADSL":"ADSL (8 mega)","DISTANZA_CALCOLATA":"2768.89","CLASSE_DISTANZA":"2500-2899","POTENZA_SEGNALE":"5749.63","POPOLAZIONE_SEZIONE": "11"}
			},
		 		{ "type" : "Feature",
				"geometry" : {
					"type" : "Point",
					"coordinates" : [7.64876,44.38464]},
			"properties" : { "ANNO":"2010","ID_SEZIONE":"18436","ISTAT_COMUNE_SEZ":"4016","COMUNE_SEZ":"BEINETTE","PROVINCIA":"CN","ID_CENTRALE":"135","NOME_CENTRALE":"BEINETTE","ISTAT_COMUNE_CENTR":"4016","COMUNE_CENTR":"BEINETTE","PROVINCIA_CENTR":"CN","INDIRIZZO_CENTRALE":"PIAZZA DIVISIONE CUNEENSE","LATITUDINE_SEZIONE":"44.38464","LONGITUDINE_SEZIONE":"7.64876","POS_X_SEZIONE":"392367.64653","POS_Y_SEZIONE":"4915483.64490","LATITUDINE_CENTRALE":"44.36157","LONGITUDINE_CENTRALE":"7.64699","POS_X_CENTRALE":"392184.00000","POS_Y_CENTRALE":"4912923.00000","TIPO_ADSL":"ADSL_1","DESCRIZIONE_TIPO_ADSL":"ADSL (8 mega)","DISTANZA_CALCOLATA":"2567.22","CLASSE_DISTANZA":"2500-2899","POTENZA_SEGNALE":"5749.63","POPOLAZIONE_SEZIONE": "23"}
			},
		 		{ "type" : "Feature",
				"geometry" : {
					"type" : "Point",
					"coordinates" : [7.63500,44.37304]},
			"properties" : { "ANNO":"2010","ID_SEZIONE":"18457","ISTAT_COMUNE_SEZ":"4016","COMUNE_SEZ":"BEINETTE","PROVINCIA":"CN","ID_CENTRALE":"135","NOME_CENTRALE":"BEINETTE","ISTAT_COMUNE_CENTR":"4016","COMUNE_CENTR":"BEINETTE","PROVINCIA_CENTR":"CN","INDIRIZZO_CENTRALE":"PIAZZA DIVISIONE CUNEENSE","LATITUDINE_SEZIONE":"44.37304","LONGITUDINE_SEZIONE":"7.63500","POS_X_SEZIONE":"391250.12103","POS_Y_SEZIONE":"4914213.14199","LATITUDINE_CENTRALE":"44.36157","LONGITUDINE_CENTRALE":"7.64699","POS_X_CENTRALE":"392184.00000","POS_Y_CENTRALE":"4912923.00000","TIPO_ADSL":"ADSL_1","DESCRIZIONE_TIPO_ADSL":"ADSL (8 mega)","DISTANZA_CALCOLATA":"1592.67","CLASSE_DISTANZA":"1300-1699","POTENZA_SEGNALE":"7000","POPOLAZIONE_SEZIONE": "43"}
			},
		 		{ "type" : "Feature",
				"geometry" : {
					"type" : "Point",
					"coordinates" : [7.64764,44.36121]},
			"properties" : { "ANNO":"2010","ID_SEZIONE":"20176","ISTAT_COMUNE_SEZ":"4016","COMUNE_SEZ":"BEINETTE","PROVINCIA":"CN","ID_CENTRALE":"135","NOME_CENTRALE":"BEINETTE","ISTAT_COMUNE_CENTR":"4016","COMUNE_CENTR":"BEINETTE","PROVINCIA_CENTR":"CN","INDIRIZZO_CENTRALE":"PIAZZA DIVISIONE CUNEENSE","LATITUDINE_SEZIONE":"44.36121","LONGITUDINE_SEZIONE":"7.64764","POS_X_SEZIONE":"392235.74407","POS_Y_SEZIONE":"4912882.14372","LATITUDINE_CENTRALE":"44.36157","LONGITUDINE_CENTRALE":"7.64699","POS_X_CENTRALE":"392184.00000","POS_Y_CENTRALE":"4912923.00000","TIPO_ADSL":"ADSL_1","DESCRIZIONE_TIPO_ADSL":"ADSL (8 mega)","DISTANZA_CALCOLATA":"65.93","CLASSE_DISTANZA":"0-99","POTENZA_SEGNALE":"7000","POPOLAZIONE_SEZIONE": "412"}
			},
		 		{ "type" : "Feature",
				"geometry" : {
					"type" : "Point",
					"coordinates" : [7.64161,44.36748]},
			"properties" : { "ANNO":"2010","ID_SEZIONE":"21195","ISTAT_COMUNE_SEZ":"4016","COMUNE_SEZ":"BEINETTE","PROVINCIA":"CN","ID_CENTRALE":"135","NOME_CENTRALE":"BEINETTE","ISTAT_COMUNE_CENTR":"4016","COMUNE_CENTR":"BEINETTE","PROVINCIA_CENTR":"CN","INDIRIZZO_CENTRALE":"PIAZZA DIVISIONE CUNEENSE","LATITUDINE_SEZIONE":"44.36748","LONGITUDINE_SEZIONE":"7.64161","POS_X_SEZIONE":"391766.29178","POS_Y_SEZIONE":"4913586.14269","LATITUDINE_CENTRALE":"44.36157","LONGITUDINE_CENTRALE":"7.64699","POS_X_CENTRALE":"392184.00000","POS_Y_CENTRALE":"4912923.00000","TIPO_ADSL":"ADSL_1","DESCRIZIONE_TIPO_ADSL":"ADSL (8 mega)","DISTANZA_CALCOLATA":"783.73","CLASSE_DISTANZA":"500-899","POTENZA_SEGNALE":"7000","POPOLAZIONE_SEZIONE": "416"}
			},
		 		{ "type" : "Feature",
				"geometry" : {
					"type" : "Point",
					"coordinates" : [7.64366,44.36518]},
			"properties" : { "ANNO":"2010","ID_SEZIONE":"22477","ISTAT_COMUNE_SEZ":"4016","COMUNE_SEZ":"BEINETTE","PROVINCIA":"CN","ID_CENTRALE":"135","NOME_CENTRALE":"BEINETTE","ISTAT_COMUNE_CENTR":"4016","COMUNE_CENTR":"BEINETTE","PROVINCIA_CENTR":"CN","INDIRIZZO_CENTRALE":"PIAZZA DIVISIONE CUNEENSE","LATITUDINE_SEZIONE":"44.36518","LONGITUDINE_SEZIONE":"7.64366","POS_X_SEZIONE":"391925.48435","POS_Y_SEZIONE":"4913328.64304","LATITUDINE_CENTRALE":"44.36157","LONGITUDINE_CENTRALE":"7.64699","POS_X_CENTRALE":"392184.00000","POS_Y_CENTRALE":"4912923.00000","TIPO_ADSL":"ADSL_1","DESCRIZIONE_TIPO_ADSL":"ADSL (8 mega)","DISTANZA_CALCOLATA":"481.02","CLASSE_DISTANZA":"100-499","POTENZA_SEGNALE":"7000","POPOLAZIONE_SEZIONE": "524"}
			},
		 		{ "type" : "Feature",
				"geometry" : {
					"type" : "Point",
					"coordinates" : [7.66010,44.35090]},
			"properties" : { "ANNO":"2010","ID_SEZIONE":"26396","ISTAT_COMUNE_SEZ":"4016","COMUNE_SEZ":"BEINETTE","PROVINCIA":"CN","ID_CENTRALE":"135","NOME_CENTRALE":"BEINETTE","ISTAT_COMUNE_CENTR":"4016","COMUNE_CENTR":"BEINETTE","PROVINCIA_CENTR":"CN","INDIRIZZO_CENTRALE":"PIAZZA DIVISIONE CUNEENSE","LATITUDINE_SEZIONE":"44.35090","LONGITUDINE_SEZIONE":"7.66010","POS_X_SEZIONE":"393209.79796","POS_Y_SEZIONE":"4911721.14634","LATITUDINE_CENTRALE":"44.36157","LONGITUDINE_CENTRALE":"7.64699","POS_X_CENTRALE":"392184.00000","POS_Y_CENTRALE":"4912923.00000","TIPO_ADSL":"ADSL_1","DESCRIZIONE_TIPO_ADSL":"ADSL (8 mega)","DISTANZA_CALCOLATA":"1580.1","CLASSE_DISTANZA":"1300-1699","POTENZA_SEGNALE":"7000","POPOLAZIONE_SEZIONE": "110"}
			},
		 		{ "type" : "Feature",
				"geometry" : {
					"type" : "Point",
					"coordinates" : [7.67464,44.36820]},
			"properties" : { "ANNO":"2010","ID_SEZIONE":"32644","ISTAT_COMUNE_SEZ":"4016","COMUNE_SEZ":"BEINETTE","PROVINCIA":"CN","ID_CENTRALE":"135","NOME_CENTRALE":"BEINETTE","ISTAT_COMUNE_CENTR":"4016","COMUNE_CENTR":"BEINETTE","PROVINCIA_CENTR":"CN","INDIRIZZO_CENTRALE":"PIAZZA DIVISIONE CUNEENSE","LATITUDINE_SEZIONE":"44.36820","LONGITUDINE_SEZIONE":"7.67464","POS_X_SEZIONE":"394399.68288","POS_Y_SEZIONE":"4913623.64925","LATITUDINE_CENTRALE":"44.36157","LONGITUDINE_CENTRALE":"7.64699","POS_X_CENTRALE":"392184.00000","POS_Y_CENTRALE":"4912923.00000","TIPO_ADSL":"ADSL_1","DESCRIZIONE_TIPO_ADSL":"ADSL (8 mega)","DISTANZA_CALCOLATA":"2323.82","CLASSE_DISTANZA":"2100-2499","POTENZA_SEGNALE":"6500.38","POPOLAZIONE_SEZIONE": "16"}
			}
		 		]
	}
		